{"textAnnotations": [{"locale": "en", "description": "SYNERBY\n", "boundingPoly": {"vertices": [{"y": 426, "x": 515}, {"y": 426, "x": 877}, {"y": 534, "x": 877}, {"y": 534, "x": 515}]}}, {"description": "SYNERBY", "boundingPoly": {"vertices": [{"y": 511, "x": 877}, {"y": 534, "x": 521}, {"y": 449, "x": 515}, {"y": 426, "x": 872}]}}], "fullTextAnnotation": {"text": "SYNERBY\n", "pages": [{"width": 1224, "property": {"detectedLanguages": [{"languageCode": "en", "confidence": 1.0}]}, "blocks": [{"boundingBox": {"vertices": [{"y": 511, "x": 877}, {"y": 534, "x": 521}, {"y": 449, "x": 515}, {"y": 426, "x": 872}]}, "blockType": "TEXT", "property": {"detectedLanguages": [{"languageCode": "en", "confidence": 1.0}]}, "paragraphs": [{"boundingBox": {"vertices": [{"y": 511, "x": 877}, {"y": 534, "x": 521}, {"y": 449, "x": 515}, {"y": 426, "x": 872}]}, "property": {"detectedLanguages": [{"languageCode": "en", "confidence": 1.0}]}, "words": [{"boundingBox": {"vertices": [{"y": 511, "x": 877}, {"y": 534, "x": 521}, {"y": 449, "x": 515}, {"y": 426, "x": 872}]}, "symbols": [{"boundingBox": {"vertices": [{"y": 511, "x": 877}, {"y": 521, "x": 714}, {"y": 437, "x": 709}, {"y": 426, "x": 872}]}, "text": "S", "property": {"detectedLanguages": [{"languageCode": "en"}]}}, {"boundingBox": {"vertices": [{"y": 522, "x": 713}, {"y": 524, "x": 686}, {"y": 439, "x": 681}, {"y": 437, "x": 708}]}, "text": "Y", "property": {"detectedLanguages": [{"languageCode": "en"}]}}, {"boundingBox": {"vertices": [{"y": 523, "x": 685}, {"y": 525, "x": 656}, {"y": 440, "x": 651}, {"y": 438, "x": 680}]}, "text": "N", "property": {"detectedLanguages": [{"languageCode": "en"}]}}, {"boundingBox": {"vertices": [{"y": 525, "x": 655}, {"y": 527, "x": 628}, {"y": 442, "x": 623}, {"y": 440, "x": 650}]}, "text": "E", "property": {"detectedLanguages": [{"languageCode": "en"}]}}, {"boundingBox": {"vertices": [{"y": 527, "x": 628}, {"y": 529, "x": 601}, {"y": 444, "x": 596}, {"y": 442, "x": 623}]}, "text": "R", "property": {"detectedLanguages": [{"languageCode": "en"}]}}, {"boundingBox": {"vertices": [{"y": 529, "x": 600}, {"y": 532, "x": 557}, {"y": 447, "x": 552}, {"y": 444, "x": 595}]}, "text": "B", "property": {"detectedLanguages": [{"languageCode": "en"}]}}, {"boundingBox": {"vertices": [{"y": 532, "x": 556}, {"y": 534, "x": 521}, {"y": 449, "x": 516}, {"y": 447, "x": 551}]}, "text": "Y", "property": {"detectedBreak": {"type": "EOL_SURE_SPACE"}, "detectedLanguages": [{"languageCode": "en"}]}}], "property": {"detectedLanguages": [{"languageCode": "en"}]}}]}]}], "height": 1632}]}}