{"textAnnotations": [{"locale": "und", "description": "Tandam\nAFAT\n", "boundingPoly": {"vertices": [{"y": 75, "x": 10}, {"y": 75, "x": 166}, {"y": 349, "x": 166}, {"y": 349, "x": 10}]}}, {"description": "Tandam", "boundingPoly": {"vertices": [{"y": 331, "x": 10}, {"y": 282, "x": 69}, {"y": 299, "x": 84}, {"y": 349, "x": 25}]}}, {"description": "AFAT", "boundingPoly": {"vertices": [{"y": 82, "x": 166}, {"y": 110, "x": 142}, {"y": 103, "x": 134}, {"y": 75, "x": 158}]}}], "fullTextAnnotation": {"text": "Tandam\nAFAT\n", "pages": [{"width": 333, "blocks": [{"boundingBox": {"vertices": [{"y": 331, "x": 10}, {"y": 282, "x": 69}, {"y": 299, "x": 84}, {"y": 349, "x": 25}]}, "blockType": "TEXT", "paragraphs": [{"boundingBox": {"vertices": [{"y": 331, "x": 10}, {"y": 282, "x": 69}, {"y": 299, "x": 84}, {"y": 349, "x": 25}]}, "words": [{"boundingBox": {"vertices": [{"y": 331, "x": 10}, {"y": 282, "x": 69}, {"y": 299, "x": 84}, {"y": 349, "x": 25}]}, "symbols": [{"boundingBox": {"vertices": [{"y": 331, "x": 10}, {"y": 313, "x": 32}, {"y": 331, "x": 46}, {"y": 349, "x": 25}]}, "text": "T"}, {"boundingBox": {"vertices": [{"y": 312, "x": 33}, {"y": 304, "x": 42}, {"y": 322, "x": 57}, {"y": 330, "x": 48}]}, "text": "a"}, {"boundingBox": {"vertices": [{"y": 304, "x": 43}, {"y": 302, "x": 45}, {"y": 320, "x": 60}, {"y": 322, "x": 58}]}, "text": "n"}, {"boundingBox": {"vertices": [{"y": 301, "x": 46}, {"y": 296, "x": 52}, {"y": 314, "x": 67}, {"y": 319, "x": 61}]}, "text": "d"}, {"boundingBox": {"vertices": [{"y": 295, "x": 53}, {"y": 291, "x": 58}, {"y": 308, "x": 73}, {"y": 313, "x": 68}]}, "text": "a"}, {"boundingBox": {"vertices": [{"y": 290, "x": 59}, {"y": 282, "x": 69}, {"y": 299, "x": 84}, {"y": 308, "x": 74}]}, "text": "m", "property": {"detectedBreak": {"type": "EOL_SURE_SPACE"}}}]}]}]}, {"boundingBox": {"vertices": [{"y": 82, "x": 166}, {"y": 110, "x": 142}, {"y": 103, "x": 134}, {"y": 75, "x": 158}]}, "blockType": "TEXT", "paragraphs": [{"boundingBox": {"vertices": [{"y": 82, "x": 166}, {"y": 110, "x": 142}, {"y": 103, "x": 134}, {"y": 75, "x": 158}]}, "words": [{"boundingBox": {"vertices": [{"y": 82, "x": 166}, {"y": 110, "x": 142}, {"y": 103, "x": 134}, {"y": 75, "x": 158}]}, "symbols": [{"boundingBox": {"vertices": [{"y": 81, "x": 166}, {"y": 95, "x": 154}, {"y": 89, "x": 147}, {"y": 75, "x": 159}]}, "text": "A"}, {"boundingBox": {"vertices": [{"y": 96, "x": 152}, {"y": 102, "x": 147}, {"y": 96, "x": 140}, {"y": 90, "x": 145}]}, "text": "F"}, {"boundingBox": {"vertices": [{"y": 104, "x": 146}, {"y": 107, "x": 143}, {"y": 101, "x": 137}, {"y": 98, "x": 139}]}, "text": "A"}, {"boundingBox": {"vertices": [{"y": 107, "x": 143}, {"y": 109, "x": 141}, {"y": 103, "x": 134}, {"y": 101, "x": 136}]}, "text": "T", "property": {"detectedBreak": {"type": "EOL_SURE_SPACE"}}}]}]}]}], "height": 500}]}}