{"textAnnotations": [{"locale": "jv", "description": "CAST\nWHE\nTRUC\nWELING-MG-REP\nApex\n1759H\nPaR\nSAFE\nSOM\nSTREET\nOW\n", "boundingPoly": {"vertices": [{"y": 21, "x": 64}, {"y": 21, "x": 639}, {"y": 295, "x": 639}, {"y": 295, "x": 64}]}}, {"description": "CAST", "boundingPoly": {"vertices": [{"y": 30, "x": 606}, {"y": 21, "x": 636}, {"y": 31, "x": 639}, {"y": 40, "x": 609}]}}, {"description": "WHE", "boundingPoly": {"vertices": [{"y": 40, "x": 613}, {"y": 33, "x": 637}, {"y": 41, "x": 639}, {"y": 48, "x": 615}]}}, {"description": "TRUC", "boundingPoly": {"vertices": [{"y": 51, "x": 613}, {"y": 44, "x": 636}, {"y": 53, "x": 639}, {"y": 60, "x": 616}]}}, {"description": "WELING-MG-REP", "boundingPoly": {"vertices": [{"y": 66, "x": 584}, {"y": 52, "x": 637}, {"y": 59, "x": 639}, {"y": 73, "x": 586}]}}, {"description": "Apex", "boundingPoly": {"vertices": [{"y": 176, "x": 595}, {"y": 175, "x": 635}, {"y": 182, "x": 635}, {"y": 183, "x": 595}]}}, {"description": "1759H", "boundingPoly": {"vertices": [{"y": 236, "x": 65}, {"y": 239, "x": 87}, {"y": 248, "x": 86}, {"y": 245, "x": 64}]}}, {"description": "PaR", "boundingPoly": {"vertices": [{"y": 237, "x": 481}, {"y": 237, "x": 488}, {"y": 241, "x": 488}, {"y": 241, "x": 481}]}}, {"description": "SAFE", "boundingPoly": {"vertices": [{"y": 240, "x": 481}, {"y": 241, "x": 508}, {"y": 259, "x": 508}, {"y": 258, "x": 481}]}}, {"description": "SOM", "boundingPoly": {"vertices": [{"y": 255, "x": 479}, {"y": 256, "x": 500}, {"y": 272, "x": 499}, {"y": 271, "x": 478}]}}, {"description": "STREET", "boundingPoly": {"vertices": [{"y": 269, "x": 482}, {"y": 270, "x": 502}, {"y": 281, "x": 502}, {"y": 280, "x": 482}]}}, {"description": "OW", "boundingPoly": {"vertices": [{"y": 287, "x": 480}, {"y": 288, "x": 500}, {"y": 295, "x": 499}, {"y": 294, "x": 479}]}}], "fullTextAnnotation": {"text": "CAST\nWHE\nTRUC\nWELING-MG-REP\nApex\n1759H\nPaR\nSAFE\nSOM\nSTREET\nOW\n", "pages": [{"width": 640, "property": {"detectedLanguages": [{"languageCode": "jv", "confidence": 0.25}, {"languageCode": "en", "confidence": 0.11999999731779099}]}, "blocks": [{"boundingBox": {"vertices": [{"y": 38, "x": 576}, {"y": 23, "x": 629}, {"y": 59, "x": 639}, {"y": 74, "x": 586}]}, "blockType": "TEXT", "property": {"detectedLanguages": [{"languageCode": "jv", "confidence": 0.5400000214576721}]}, "paragraphs": [{"boundingBox": {"vertices": [{"y": 38, "x": 576}, {"y": 23, "x": 629}, {"y": 59, "x": 639}, {"y": 74, "x": 586}]}, "property": {"detectedLanguages": [{"languageCode": "jv", "confidence": 0.5400000214576721}]}, "words": [{"boundingBox": {"vertices": [{"y": 30, "x": 606}, {"y": 21, "x": 636}, {"y": 31, "x": 639}, {"y": 40, "x": 609}]}, "symbols": [{"boundingBox": {"vertices": [{"y": 30, "x": 606}, {"y": 26, "x": 621}, {"y": 35, "x": 624}, {"y": 40, "x": 609}]}, "text": "C"}, {"boundingBox": {"vertices": [{"y": 25, "x": 622}, {"y": 24, "x": 625}, {"y": 34, "x": 628}, {"y": 35, "x": 625}]}, "text": "A"}, {"boundingBox": {"vertices": [{"y": 24, "x": 626}, {"y": 23, "x": 630}, {"y": 33, "x": 633}, {"y": 34, "x": 629}]}, "text": "S"}, {"boundingBox": {"vertices": [{"y": 23, "x": 631}, {"y": 22, "x": 636}, {"y": 31, "x": 639}, {"y": 33, "x": 634}]}, "text": "T", "property": {"detectedBreak": {"type": "EOL_SURE_SPACE"}}}]}, {"boundingBox": {"vertices": [{"y": 40, "x": 613}, {"y": 33, "x": 637}, {"y": 41, "x": 639}, {"y": 48, "x": 615}]}, "symbols": [{"boundingBox": {"vertices": [{"y": 40, "x": 613}, {"y": 37, "x": 624}, {"y": 44, "x": 625}, {"y": 47, "x": 615}]}, "text": "W"}, {"boundingBox": {"vertices": [{"y": 37, "x": 625}, {"y": 36, "x": 629}, {"y": 43, "x": 631}, {"y": 44, "x": 627}]}, "text": "H"}, {"boundingBox": {"vertices": [{"y": 36, "x": 630}, {"y": 34, "x": 637}, {"y": 41, "x": 639}, {"y": 43, "x": 632}]}, "text": "E", "property": {"detectedBreak": {"type": "EOL_SURE_SPACE"}}}]}, {"boundingBox": {"vertices": [{"y": 51, "x": 613}, {"y": 44, "x": 636}, {"y": 53, "x": 639}, {"y": 60, "x": 616}]}, "symbols": [{"boundingBox": {"vertices": [{"y": 51, "x": 613}, {"y": 49, "x": 621}, {"y": 56, "x": 623}, {"y": 59, "x": 615}]}, "text": "T"}, {"boundingBox": {"vertices": [{"y": 49, "x": 622}, {"y": 47, "x": 629}, {"y": 55, "x": 631}, {"y": 57, "x": 624}]}, "text": "R"}, {"boundingBox": {"vertices": [{"y": 47, "x": 630}, {"y": 45, "x": 637}, {"y": 53, "x": 639}, {"y": 55, "x": 632}]}, "text": "U"}, {"boundingBox": {"vertices": [{"y": 43, "x": 638}, {"y": 43, "x": 639}, {"y": 52, "x": 639}, {"y": 52, "x": 638}]}, "text": "C", "property": {"detectedBreak": {"type": "EOL_SURE_SPACE"}}}]}, {"boundingBox": {"vertices": [{"y": 66, "x": 584}, {"y": 52, "x": 637}, {"y": 59, "x": 639}, {"y": 73, "x": 586}]}, "symbols": [{"boundingBox": {"vertices": [{"y": 67, "x": 584}, {"y": 65, "x": 592}, {"y": 71, "x": 593}, {"y": 73, "x": 586}]}, "text": "W", "property": {"detectedLanguages": [{"languageCode": "jv"}]}}, {"boundingBox": {"vertices": [{"y": 65, "x": 593}, {"y": 64, "x": 595}, {"y": 70, "x": 596}, {"y": 71, "x": 595}]}, "text": "E", "property": {"detectedLanguages": [{"languageCode": "jv"}]}}, {"boundingBox": {"vertices": [{"y": 64, "x": 596}, {"y": 64, "x": 597}, {"y": 70, "x": 598}, {"y": 70, "x": 598}]}, "text": "L", "property": {"detectedLanguages": [{"languageCode": "jv"}]}}, {"boundingBox": {"vertices": [{"y": 63, "x": 598}, {"y": 62, "x": 603}, {"y": 68, "x": 604}, {"y": 69, "x": 600}]}, "text": "I", "property": {"detectedLanguages": [{"languageCode": "jv"}]}}, {"boundingBox": {"vertices": [{"y": 62, "x": 603}, {"y": 61, "x": 605}, {"y": 67, "x": 606}, {"y": 68, "x": 605}]}, "text": "N", "property": {"detectedLanguages": [{"languageCode": "jv"}]}}, {"boundingBox": {"vertices": [{"y": 60, "x": 606}, {"y": 59, "x": 608}, {"y": 65, "x": 609}, {"y": 66, "x": 608}]}, "text": "G", "property": {"detectedLanguages": [{"languageCode": "jv"}]}}, {"boundingBox": {"vertices": [{"y": 60, "x": 609}, {"y": 59, "x": 611}, {"y": 65, "x": 612}, {"y": 66, "x": 611}]}, "text": "-", "property": {"detectedLanguages": [{"languageCode": "jv"}]}}, {"boundingBox": {"vertices": [{"y": 60, "x": 612}, {"y": 59, "x": 617}, {"y": 65, "x": 618}, {"y": 66, "x": 614}]}, "text": "M", "property": {"detectedLanguages": [{"languageCode": "jv"}]}}, {"boundingBox": {"vertices": [{"y": 58, "x": 618}, {"y": 57, "x": 623}, {"y": 63, "x": 624}, {"y": 64, "x": 620}]}, "text": "G", "property": {"detectedLanguages": [{"languageCode": "jv"}]}}, {"boundingBox": {"vertices": [{"y": 57, "x": 624}, {"y": 56, "x": 628}, {"y": 62, "x": 629}, {"y": 63, "x": 626}]}, "text": "-", "property": {"detectedLanguages": [{"languageCode": "jv"}]}}, {"boundingBox": {"vertices": [{"y": 55, "x": 629}, {"y": 53, "x": 635}, {"y": 59, "x": 636}, {"y": 61, "x": 631}]}, "text": "R", "property": {"detectedLanguages": [{"languageCode": "jv"}]}}, {"boundingBox": {"vertices": [{"y": 54, "x": 635}, {"y": 54, "x": 637}, {"y": 60, "x": 637}, {"y": 60, "x": 635}]}, "text": "E", "property": {"detectedLanguages": [{"languageCode": "jv"}]}}, {"boundingBox": {"vertices": [{"y": 53, "x": 636}, {"y": 52, "x": 638}, {"y": 58, "x": 639}, {"y": 59, "x": 638}]}, "text": "P", "property": {"detectedBreak": {"type": "EOL_SURE_SPACE"}, "detectedLanguages": [{"languageCode": "jv"}]}}], "property": {"detectedLanguages": [{"languageCode": "jv"}]}}]}]}, {"boundingBox": {"vertices": [{"y": 176, "x": 595}, {"y": 175, "x": 635}, {"y": 182, "x": 635}, {"y": 183, "x": 595}]}, "blockType": "TEXT", "paragraphs": [{"boundingBox": {"vertices": [{"y": 176, "x": 595}, {"y": 175, "x": 635}, {"y": 182, "x": 635}, {"y": 183, "x": 595}]}, "words": [{"boundingBox": {"vertices": [{"y": 176, "x": 595}, {"y": 175, "x": 635}, {"y": 182, "x": 635}, {"y": 183, "x": 595}]}, "symbols": [{"boundingBox": {"vertices": [{"y": 176, "x": 595}, {"y": 176, "x": 611}, {"y": 183, "x": 611}, {"y": 183, "x": 595}]}, "text": "A"}, {"boundingBox": {"vertices": [{"y": 176, "x": 612}, {"y": 176, "x": 624}, {"y": 183, "x": 624}, {"y": 183, "x": 612}]}, "text": "p"}, {"boundingBox": {"vertices": [{"y": 175, "x": 625}, {"y": 175, "x": 633}, {"y": 182, "x": 633}, {"y": 182, "x": 625}]}, "text": "e"}, {"boundingBox": {"vertices": [{"y": 175, "x": 634}, {"y": 175, "x": 635}, {"y": 182, "x": 635}, {"y": 182, "x": 634}]}, "text": "x", "property": {"detectedBreak": {"type": "EOL_SURE_SPACE"}}}]}]}]}, {"boundingBox": {"vertices": [{"y": 236, "x": 65}, {"y": 239, "x": 87}, {"y": 248, "x": 86}, {"y": 245, "x": 64}]}, "blockType": "TEXT", "paragraphs": [{"boundingBox": {"vertices": [{"y": 236, "x": 65}, {"y": 239, "x": 87}, {"y": 248, "x": 86}, {"y": 245, "x": 64}]}, "words": [{"boundingBox": {"vertices": [{"y": 236, "x": 65}, {"y": 239, "x": 87}, {"y": 248, "x": 86}, {"y": 245, "x": 64}]}, "symbols": [{"boundingBox": {"vertices": [{"y": 236, "x": 65}, {"y": 237, "x": 73}, {"y": 246, "x": 72}, {"y": 245, "x": 64}]}, "text": "1"}, {"boundingBox": {"vertices": [{"y": 237, "x": 74}, {"y": 237, "x": 74}, {"y": 246, "x": 73}, {"y": 246, "x": 73}]}, "text": "7"}, {"boundingBox": {"vertices": [{"y": 238, "x": 75}, {"y": 238, "x": 76}, {"y": 247, "x": 75}, {"y": 247, "x": 74}]}, "text": "5"}, {"boundingBox": {"vertices": [{"y": 238, "x": 77}, {"y": 238, "x": 79}, {"y": 247, "x": 78}, {"y": 247, "x": 76}]}, "text": "9"}, {"boundingBox": {"vertices": [{"y": 238, "x": 80}, {"y": 239, "x": 87}, {"y": 248, "x": 86}, {"y": 247, "x": 79}]}, "text": "H", "property": {"detectedBreak": {"type": "EOL_SURE_SPACE"}}}]}]}]}, {"boundingBox": {"vertices": [{"y": 237, "x": 481}, {"y": 237, "x": 488}, {"y": 241, "x": 488}, {"y": 241, "x": 481}]}, "blockType": "TEXT", "paragraphs": [{"boundingBox": {"vertices": [{"y": 237, "x": 481}, {"y": 237, "x": 488}, {"y": 241, "x": 488}, {"y": 241, "x": 481}]}, "words": [{"boundingBox": {"vertices": [{"y": 237, "x": 481}, {"y": 237, "x": 488}, {"y": 241, "x": 488}, {"y": 241, "x": 481}]}, "symbols": [{"boundingBox": {"vertices": [{"y": 237, "x": 481}, {"y": 237, "x": 484}, {"y": 241, "x": 484}, {"y": 241, "x": 481}]}, "text": "P"}, {"boundingBox": {"vertices": [{"y": 237, "x": 485}, {"y": 237, "x": 486}, {"y": 241, "x": 486}, {"y": 241, "x": 485}]}, "text": "a"}, {"boundingBox": {"vertices": [{"y": 237, "x": 487}, {"y": 237, "x": 488}, {"y": 241, "x": 488}, {"y": 241, "x": 487}]}, "text": "R", "property": {"detectedBreak": {"type": "EOL_SURE_SPACE"}}}]}]}]}, {"boundingBox": {"vertices": [{"y": 240, "x": 479}, {"y": 241, "x": 508}, {"y": 281, "x": 507}, {"y": 280, "x": 478}]}, "blockType": "TEXT", "property": {"detectedLanguages": [{"languageCode": "en", "confidence": 0.46000000834465027}]}, "paragraphs": [{"boundingBox": {"vertices": [{"y": 240, "x": 479}, {"y": 241, "x": 508}, {"y": 281, "x": 507}, {"y": 280, "x": 478}]}, "property": {"detectedLanguages": [{"languageCode": "en", "confidence": 0.46000000834465027}]}, "words": [{"boundingBox": {"vertices": [{"y": 240, "x": 481}, {"y": 241, "x": 508}, {"y": 259, "x": 508}, {"y": 258, "x": 481}]}, "symbols": [{"boundingBox": {"vertices": [{"y": 240, "x": 481}, {"y": 240, "x": 481}, {"y": 240, "x": 481}, {"y": 240, "x": 481}]}, "text": "S"}, {"boundingBox": {"vertices": [{"y": 240, "x": 483}, {"y": 240, "x": 484}, {"y": 240, "x": 484}, {"y": 240, "x": 483}]}, "text": "A"}, {"boundingBox": {"vertices": [{"y": 240, "x": 486}, {"y": 240, "x": 495}, {"y": 258, "x": 495}, {"y": 258, "x": 486}]}, "text": "F"}, {"boundingBox": {"vertices": [{"y": 240, "x": 497}, {"y": 240, "x": 508}, {"y": 258, "x": 508}, {"y": 258, "x": 497}]}, "text": "E", "property": {"detectedBreak": {"type": "EOL_SURE_SPACE"}}}]}, {"boundingBox": {"vertices": [{"y": 255, "x": 479}, {"y": 256, "x": 500}, {"y": 272, "x": 499}, {"y": 271, "x": 478}]}, "symbols": [{"boundingBox": {"vertices": [{"y": 256, "x": 479}, {"y": 256, "x": 489}, {"y": 271, "x": 488}, {"y": 271, "x": 478}]}, "text": "S"}, {"boundingBox": {"vertices": [{"y": 256, "x": 490}, {"y": 256, "x": 494}, {"y": 271, "x": 493}, {"y": 271, "x": 489}]}, "text": "O"}, {"boundingBox": {"vertices": [{"y": 256, "x": 495}, {"y": 256, "x": 500}, {"y": 271, "x": 499}, {"y": 271, "x": 494}]}, "text": "M", "property": {"detectedBreak": {"type": "EOL_SURE_SPACE"}}}]}, {"boundingBox": {"vertices": [{"y": 269, "x": 482}, {"y": 270, "x": 502}, {"y": 281, "x": 502}, {"y": 280, "x": 482}]}, "symbols": [{"boundingBox": {"vertices": [{"y": 269, "x": 482}, {"y": 269, "x": 488}, {"y": 279, "x": 488}, {"y": 279, "x": 482}]}, "text": "S", "property": {"detectedLanguages": [{"languageCode": "en"}]}}, {"boundingBox": {"vertices": [{"y": 269, "x": 489}, {"y": 269, "x": 490}, {"y": 279, "x": 490}, {"y": 279, "x": 489}]}, "text": "T", "property": {"detectedLanguages": [{"languageCode": "en"}]}}, {"boundingBox": {"vertices": [{"y": 269, "x": 491}, {"y": 269, "x": 493}, {"y": 279, "x": 493}, {"y": 279, "x": 491}]}, "text": "R", "property": {"detectedLanguages": [{"languageCode": "en"}]}}, {"boundingBox": {"vertices": [{"y": 270, "x": 494}, {"y": 270, "x": 495}, {"y": 280, "x": 495}, {"y": 280, "x": 494}]}, "text": "E", "property": {"detectedLanguages": [{"languageCode": "en"}]}}, {"boundingBox": {"vertices": [{"y": 270, "x": 496}, {"y": 270, "x": 499}, {"y": 280, "x": 499}, {"y": 280, "x": 496}]}, "text": "E", "property": {"detectedLanguages": [{"languageCode": "en"}]}}, {"boundingBox": {"vertices": [{"y": 270, "x": 500}, {"y": 270, "x": 502}, {"y": 280, "x": 502}, {"y": 280, "x": 500}]}, "text": "T", "property": {"detectedBreak": {"type": "EOL_SURE_SPACE"}, "detectedLanguages": [{"languageCode": "en"}]}}], "property": {"detectedLanguages": [{"languageCode": "en"}]}}]}]}, {"boundingBox": {"vertices": [{"y": 287, "x": 480}, {"y": 288, "x": 500}, {"y": 295, "x": 499}, {"y": 294, "x": 479}]}, "blockType": "TEXT", "paragraphs": [{"boundingBox": {"vertices": [{"y": 287, "x": 480}, {"y": 288, "x": 500}, {"y": 295, "x": 499}, {"y": 294, "x": 479}]}, "words": [{"boundingBox": {"vertices": [{"y": 287, "x": 480}, {"y": 288, "x": 500}, {"y": 295, "x": 499}, {"y": 294, "x": 479}]}, "symbols": [{"boundingBox": {"vertices": [{"y": 287, "x": 480}, {"y": 287, "x": 486}, {"y": 294, "x": 485}, {"y": 294, "x": 479}]}, "text": "O"}, {"boundingBox": {"vertices": [{"y": 294, "x": 500}, {"y": 294, "x": 500}, {"y": 295, "x": 500}, {"y": 295, "x": 500}]}, "text": "W", "property": {"detectedBreak": {"type": "EOL_SURE_SPACE"}}}]}]}]}], "height": 424}]}}