{"textAnnotations": [{"locale": "en", "description": "TMLEW\noTHE BIKE\nNo\nTO THE BIKE\nP\u0100RKING TAX\nTO THE BIKE\nPAPKING TA\nSTTOIL\n", "boundingPoly": {"vertices": [{"y": 87, "x": 128}, {"y": 87, "x": 427}, {"y": 331, "x": 427}, {"y": 331, "x": 128}]}}, {"description": "TMLEW", "boundingPoly": {"vertices": [{"y": 87, "x": 129}, {"y": 89, "x": 156}, {"y": 99, "x": 155}, {"y": 97, "x": 128}]}}, {"description": "oTHE", "boundingPoly": {"vertices": [{"y": 198, "x": 282}, {"y": 195, "x": 303}, {"y": 202, "x": 304}, {"y": 205, "x": 283}]}}, {"description": "BIKE", "boundingPoly": {"vertices": [{"y": 194, "x": 308}, {"y": 191, "x": 328}, {"y": 198, "x": 329}, {"y": 201, "x": 309}]}}, {"description": "No", "boundingPoly": {"vertices": [{"y": 260, "x": 138}, {"y": 262, "x": 207}, {"y": 296, "x": 206}, {"y": 294, "x": 137}]}}, {"description": "TO", "boundingPoly": {"vertices": [{"y": 290, "x": 143}, {"y": 291, "x": 154}, {"y": 302, "x": 153}, {"y": 301, "x": 142}]}}, {"description": "THE", "boundingPoly": {"vertices": [{"y": 290, "x": 156}, {"y": 292, "x": 176}, {"y": 305, "x": 175}, {"y": 303, "x": 155}]}}, {"description": "BIKE", "boundingPoly": {"vertices": [{"y": 293, "x": 180}, {"y": 295, "x": 207}, {"y": 307, "x": 206}, {"y": 305, "x": 179}]}}, {"description": "P\u0100RKING", "boundingPoly": {"vertices": [{"y": 300, "x": 144}, {"y": 304, "x": 185}, {"y": 316, "x": 183}, {"y": 312, "x": 143}]}}, {"description": "TAX", "boundingPoly": {"vertices": [{"y": 305, "x": 187}, {"y": 307, "x": 208}, {"y": 317, "x": 207}, {"y": 315, "x": 186}]}}, {"description": "TO", "boundingPoly": {"vertices": [{"y": 309, "x": 326}, {"y": 308, "x": 343}, {"y": 319, "x": 344}, {"y": 320, "x": 327}]}}, {"description": "THE", "boundingPoly": {"vertices": [{"y": 307, "x": 345}, {"y": 306, "x": 355}, {"y": 318, "x": 356}, {"y": 319, "x": 346}]}}, {"description": "BIKE", "boundingPoly": {"vertices": [{"y": 307, "x": 357}, {"y": 306, "x": 371}, {"y": 317, "x": 372}, {"y": 318, "x": 358}]}}, {"description": "PAPKING", "boundingPoly": {"vertices": [{"y": 320, "x": 328}, {"y": 317, "x": 358}, {"y": 328, "x": 359}, {"y": 331, "x": 329}]}}, {"description": "TA", "boundingPoly": {"vertices": [{"y": 317, "x": 360}, {"y": 316, "x": 368}, {"y": 327, "x": 369}, {"y": 328, "x": 361}]}}, {"description": "STTOIL", "boundingPoly": {"vertices": [{"y": 291, "x": 427}, {"y": 318, "x": 425}, {"y": 317, "x": 415}, {"y": 290, "x": 417}]}}], "fullTextAnnotation": {"text": "TMLEW\noTHE BIKE\nNo\nTO THE BIKE\nP\u0100RKING TAX\nTO THE BIKE\nPAPKING TA\nSTTOIL\n", "pages": [{"width": 500, "property": {"detectedLanguages": [{"languageCode": "en", "confidence": 0.7799999713897705}, {"languageCode": "gd", "confidence": 0.10000000149011612}, {"languageCode": "mt", "confidence": 0.09000000357627869}]}, "blocks": [{"boundingBox": {"vertices": [{"y": 87, "x": 129}, {"y": 89, "x": 156}, {"y": 99, "x": 155}, {"y": 97, "x": 128}]}, "blockType": "TEXT", "property": {"detectedLanguages": [{"languageCode": "mt", "confidence": 1.0}]}, "paragraphs": [{"boundingBox": {"vertices": [{"y": 87, "x": 129}, {"y": 89, "x": 156}, {"y": 99, "x": 155}, {"y": 97, "x": 128}]}, "property": {"detectedLanguages": [{"languageCode": "mt", "confidence": 1.0}]}, "words": [{"boundingBox": {"vertices": [{"y": 87, "x": 129}, {"y": 89, "x": 156}, {"y": 99, "x": 155}, {"y": 97, "x": 128}]}, "symbols": [{"boundingBox": {"vertices": [{"y": 87, "x": 129}, {"y": 87, "x": 134}, {"y": 96, "x": 133}, {"y": 96, "x": 128}]}, "text": "T", "property": {"detectedLanguages": [{"languageCode": "mt"}]}}, {"boundingBox": {"vertices": [{"y": 88, "x": 135}, {"y": 88, "x": 139}, {"y": 97, "x": 138}, {"y": 97, "x": 134}]}, "text": "M", "property": {"detectedLanguages": [{"languageCode": "mt"}]}}, {"boundingBox": {"vertices": [{"y": 88, "x": 140}, {"y": 88, "x": 144}, {"y": 97, "x": 143}, {"y": 97, "x": 139}]}, "text": "L", "property": {"detectedLanguages": [{"languageCode": "mt"}]}}, {"boundingBox": {"vertices": [{"y": 89, "x": 145}, {"y": 89, "x": 149}, {"y": 98, "x": 148}, {"y": 98, "x": 144}]}, "text": "E", "property": {"detectedLanguages": [{"languageCode": "mt"}]}}, {"boundingBox": {"vertices": [{"y": 89, "x": 150}, {"y": 89, "x": 156}, {"y": 98, "x": 155}, {"y": 98, "x": 149}]}, "text": "W", "property": {"detectedBreak": {"type": "EOL_SURE_SPACE"}, "detectedLanguages": [{"languageCode": "mt"}]}}], "property": {"detectedLanguages": [{"languageCode": "mt"}]}}]}]}, {"boundingBox": {"vertices": [{"y": 198, "x": 282}, {"y": 192, "x": 328}, {"y": 199, "x": 329}, {"y": 205, "x": 283}]}, "blockType": "TEXT", "property": {"detectedLanguages": [{"languageCode": "en", "confidence": 1.0}]}, "paragraphs": [{"boundingBox": {"vertices": [{"y": 198, "x": 282}, {"y": 192, "x": 328}, {"y": 199, "x": 329}, {"y": 205, "x": 283}]}, "property": {"detectedLanguages": [{"languageCode": "en", "confidence": 1.0}]}, "words": [{"boundingBox": {"vertices": [{"y": 198, "x": 282}, {"y": 195, "x": 303}, {"y": 202, "x": 304}, {"y": 205, "x": 283}]}, "symbols": [{"boundingBox": {"vertices": [{"y": 198, "x": 282}, {"y": 197, "x": 290}, {"y": 203, "x": 291}, {"y": 204, "x": 283}]}, "text": "o", "property": {"detectedLanguages": [{"languageCode": "en"}]}}, {"boundingBox": {"vertices": [{"y": 197, "x": 291}, {"y": 196, "x": 296}, {"y": 202, "x": 297}, {"y": 203, "x": 292}]}, "text": "T", "property": {"detectedLanguages": [{"languageCode": "en"}]}}, {"boundingBox": {"vertices": [{"y": 196, "x": 297}, {"y": 196, "x": 300}, {"y": 202, "x": 301}, {"y": 202, "x": 298}]}, "text": "H", "property": {"detectedLanguages": [{"languageCode": "en"}]}}, {"boundingBox": {"vertices": [{"y": 196, "x": 301}, {"y": 196, "x": 303}, {"y": 202, "x": 304}, {"y": 202, "x": 302}]}, "text": "E", "property": {"detectedBreak": {"type": "SPACE"}, "detectedLanguages": [{"languageCode": "en"}]}}], "property": {"detectedLanguages": [{"languageCode": "en"}]}}, {"boundingBox": {"vertices": [{"y": 194, "x": 308}, {"y": 191, "x": 328}, {"y": 198, "x": 329}, {"y": 201, "x": 309}]}, "symbols": [{"boundingBox": {"vertices": [{"y": 195, "x": 308}, {"y": 194, "x": 314}, {"y": 200, "x": 315}, {"y": 201, "x": 309}]}, "text": "B", "property": {"detectedLanguages": [{"languageCode": "en"}]}}, {"boundingBox": {"vertices": [{"y": 194, "x": 315}, {"y": 194, "x": 316}, {"y": 200, "x": 317}, {"y": 200, "x": 316}]}, "text": "I", "property": {"detectedLanguages": [{"languageCode": "en"}]}}, {"boundingBox": {"vertices": [{"y": 194, "x": 317}, {"y": 193, "x": 325}, {"y": 199, "x": 326}, {"y": 200, "x": 318}]}, "text": "K", "property": {"detectedLanguages": [{"languageCode": "en"}]}}, {"boundingBox": {"vertices": [{"y": 192, "x": 326}, {"y": 192, "x": 328}, {"y": 198, "x": 329}, {"y": 198, "x": 327}]}, "text": "E", "property": {"detectedBreak": {"type": "EOL_SURE_SPACE"}, "detectedLanguages": [{"languageCode": "en"}]}}], "property": {"detectedLanguages": [{"languageCode": "en"}]}}]}]}, {"boundingBox": {"vertices": [{"y": 260, "x": 138}, {"y": 262, "x": 207}, {"y": 296, "x": 206}, {"y": 294, "x": 137}]}, "blockType": "TEXT", "paragraphs": [{"boundingBox": {"vertices": [{"y": 260, "x": 138}, {"y": 262, "x": 207}, {"y": 296, "x": 206}, {"y": 294, "x": 137}]}, "words": [{"boundingBox": {"vertices": [{"y": 260, "x": 138}, {"y": 262, "x": 207}, {"y": 296, "x": 206}, {"y": 294, "x": 137}]}, "symbols": [{"boundingBox": {"vertices": [{"y": 260, "x": 138}, {"y": 261, "x": 157}, {"y": 295, "x": 156}, {"y": 294, "x": 137}]}, "text": "N"}, {"boundingBox": {"vertices": [{"y": 261, "x": 158}, {"y": 263, "x": 207}, {"y": 297, "x": 206}, {"y": 295, "x": 157}]}, "text": "o", "property": {"detectedBreak": {"type": "EOL_SURE_SPACE"}}}]}]}]}, {"boundingBox": {"vertices": [{"y": 288, "x": 143}, {"y": 294, "x": 209}, {"y": 319, "x": 206}, {"y": 313, "x": 141}]}, "blockType": "TEXT", "property": {"detectedLanguages": [{"languageCode": "en", "confidence": 1.0}]}, "paragraphs": [{"boundingBox": {"vertices": [{"y": 288, "x": 143}, {"y": 294, "x": 209}, {"y": 319, "x": 206}, {"y": 313, "x": 141}]}, "property": {"detectedLanguages": [{"languageCode": "en", "confidence": 1.0}]}, "words": [{"boundingBox": {"vertices": [{"y": 290, "x": 143}, {"y": 291, "x": 154}, {"y": 302, "x": 153}, {"y": 301, "x": 142}]}, "symbols": [{"boundingBox": {"vertices": [{"y": 290, "x": 143}, {"y": 290, "x": 146}, {"y": 299, "x": 145}, {"y": 299, "x": 142}]}, "text": "T", "property": {"detectedLanguages": [{"languageCode": "en"}]}}, {"boundingBox": {"vertices": [{"y": 292, "x": 148}, {"y": 293, "x": 154}, {"y": 301, "x": 153}, {"y": 301, "x": 147}]}, "text": "O", "property": {"detectedBreak": {"type": "SPACE"}, "detectedLanguages": [{"languageCode": "en"}]}}], "property": {"detectedLanguages": [{"languageCode": "en"}]}}, {"boundingBox": {"vertices": [{"y": 290, "x": 156}, {"y": 292, "x": 176}, {"y": 305, "x": 175}, {"y": 303, "x": 155}]}, "symbols": [{"boundingBox": {"vertices": [{"y": 290, "x": 156}, {"y": 291, "x": 163}, {"y": 303, "x": 162}, {"y": 302, "x": 155}]}, "text": "T", "property": {"detectedLanguages": [{"languageCode": "en"}]}}, {"boundingBox": {"vertices": [{"y": 291, "x": 164}, {"y": 292, "x": 170}, {"y": 303, "x": 169}, {"y": 303, "x": 163}]}, "text": "H", "property": {"detectedLanguages": [{"languageCode": "en"}]}}, {"boundingBox": {"vertices": [{"y": 292, "x": 171}, {"y": 292, "x": 176}, {"y": 304, "x": 175}, {"y": 304, "x": 170}]}, "text": "E", "property": {"detectedBreak": {"type": "SPACE"}, "detectedLanguages": [{"languageCode": "en"}]}}], "property": {"detectedLanguages": [{"languageCode": "en"}]}}, {"boundingBox": {"vertices": [{"y": 293, "x": 180}, {"y": 295, "x": 207}, {"y": 307, "x": 206}, {"y": 305, "x": 179}]}, "symbols": [{"boundingBox": {"vertices": [{"y": 294, "x": 180}, {"y": 295, "x": 187}, {"y": 306, "x": 186}, {"y": 305, "x": 179}]}, "text": "B", "property": {"detectedLanguages": [{"languageCode": "en"}]}}, {"boundingBox": {"vertices": [{"y": 294, "x": 188}, {"y": 295, "x": 194}, {"y": 305, "x": 193}, {"y": 305, "x": 187}]}, "text": "I", "property": {"detectedLanguages": [{"languageCode": "en"}]}}, {"boundingBox": {"vertices": [{"y": 295, "x": 195}, {"y": 295, "x": 200}, {"y": 306, "x": 199}, {"y": 306, "x": 194}]}, "text": "K", "property": {"detectedLanguages": [{"languageCode": "en"}]}}, {"boundingBox": {"vertices": [{"y": 295, "x": 201}, {"y": 296, "x": 207}, {"y": 306, "x": 206}, {"y": 306, "x": 200}]}, "text": "E", "property": {"detectedBreak": {"type": "EOL_SURE_SPACE"}, "detectedLanguages": [{"languageCode": "en"}]}}], "property": {"detectedLanguages": [{"languageCode": "en"}]}}, {"boundingBox": {"vertices": [{"y": 300, "x": 144}, {"y": 304, "x": 185}, {"y": 316, "x": 183}, {"y": 312, "x": 143}]}, "symbols": [{"boundingBox": {"vertices": [{"y": 300, "x": 144}, {"y": 301, "x": 150}, {"y": 312, "x": 149}, {"y": 311, "x": 143}]}, "text": "P", "property": {"detectedLanguages": [{"languageCode": "en"}]}}, {"boundingBox": {"vertices": [{"y": 301, "x": 151}, {"y": 302, "x": 159}, {"y": 313, "x": 158}, {"y": 312, "x": 150}]}, "text": "\u0100", "property": {"detectedLanguages": [{"languageCode": "en"}]}}, {"boundingBox": {"vertices": [{"y": 302, "x": 160}, {"y": 302, "x": 163}, {"y": 313, "x": 162}, {"y": 313, "x": 159}]}, "text": "R", "property": {"detectedLanguages": [{"languageCode": "en"}]}}, {"boundingBox": {"vertices": [{"y": 303, "x": 164}, {"y": 303, "x": 168}, {"y": 314, "x": 167}, {"y": 314, "x": 163}]}, "text": "K", "property": {"detectedLanguages": [{"languageCode": "en"}]}}, {"boundingBox": {"vertices": [{"y": 303, "x": 169}, {"y": 303, "x": 172}, {"y": 314, "x": 171}, {"y": 314, "x": 168}]}, "text": "I", "property": {"detectedLanguages": [{"languageCode": "en"}]}}, {"boundingBox": {"vertices": [{"y": 304, "x": 173}, {"y": 304, "x": 176}, {"y": 315, "x": 175}, {"y": 315, "x": 172}]}, "text": "N", "property": {"detectedLanguages": [{"languageCode": "en"}]}}, {"boundingBox": {"vertices": [{"y": 304, "x": 177}, {"y": 305, "x": 185}, {"y": 316, "x": 184}, {"y": 315, "x": 176}]}, "text": "G", "property": {"detectedBreak": {"type": "SPACE"}, "detectedLanguages": [{"languageCode": "en"}]}}], "property": {"detectedLanguages": [{"languageCode": "en"}]}}, {"boundingBox": {"vertices": [{"y": 305, "x": 187}, {"y": 307, "x": 208}, {"y": 317, "x": 207}, {"y": 315, "x": 186}]}, "symbols": [{"boundingBox": {"vertices": [{"y": 305, "x": 187}, {"y": 306, "x": 194}, {"y": 316, "x": 193}, {"y": 315, "x": 186}]}, "text": "T", "property": {"detectedLanguages": [{"languageCode": "en"}]}}, {"boundingBox": {"vertices": [{"y": 306, "x": 195}, {"y": 306, "x": 198}, {"y": 316, "x": 197}, {"y": 316, "x": 194}]}, "text": "A", "property": {"detectedLanguages": [{"languageCode": "en"}]}}, {"boundingBox": {"vertices": [{"y": 306, "x": 199}, {"y": 307, "x": 208}, {"y": 317, "x": 207}, {"y": 316, "x": 198}]}, "text": "X", "property": {"detectedBreak": {"type": "EOL_SURE_SPACE"}, "detectedLanguages": [{"languageCode": "en"}]}}], "property": {"detectedLanguages": [{"languageCode": "en"}]}}]}]}, {"boundingBox": {"vertices": [{"y": 309, "x": 326}, {"y": 305, "x": 371}, {"y": 327, "x": 373}, {"y": 331, "x": 328}]}, "blockType": "TEXT", "property": {"detectedLanguages": [{"languageCode": "en", "confidence": 1.0}]}, "paragraphs": [{"boundingBox": {"vertices": [{"y": 309, "x": 326}, {"y": 305, "x": 371}, {"y": 327, "x": 373}, {"y": 331, "x": 328}]}, "property": {"detectedLanguages": [{"languageCode": "en", "confidence": 1.0}]}, "words": [{"boundingBox": {"vertices": [{"y": 309, "x": 326}, {"y": 308, "x": 343}, {"y": 319, "x": 344}, {"y": 320, "x": 327}]}, "symbols": [{"boundingBox": {"vertices": [{"y": 309, "x": 326}, {"y": 308, "x": 337}, {"y": 319, "x": 338}, {"y": 320, "x": 327}]}, "text": "T", "property": {"detectedLanguages": [{"languageCode": "en"}]}}, {"boundingBox": {"vertices": [{"y": 308, "x": 338}, {"y": 308, "x": 343}, {"y": 319, "x": 344}, {"y": 319, "x": 339}]}, "text": "O", "property": {"detectedBreak": {"type": "SPACE"}, "detectedLanguages": [{"languageCode": "en"}]}}], "property": {"detectedLanguages": [{"languageCode": "en"}]}}, {"boundingBox": {"vertices": [{"y": 307, "x": 345}, {"y": 306, "x": 355}, {"y": 318, "x": 356}, {"y": 319, "x": 346}]}, "symbols": [{"boundingBox": {"vertices": [{"y": 308, "x": 345}, {"y": 308, "x": 347}, {"y": 319, "x": 348}, {"y": 319, "x": 346}]}, "text": "T", "property": {"detectedLanguages": [{"languageCode": "en"}]}}, {"boundingBox": {"vertices": [{"y": 307, "x": 348}, {"y": 307, "x": 351}, {"y": 318, "x": 352}, {"y": 318, "x": 349}]}, "text": "H", "property": {"detectedLanguages": [{"languageCode": "en"}]}}, {"boundingBox": {"vertices": [{"y": 307, "x": 352}, {"y": 307, "x": 355}, {"y": 318, "x": 356}, {"y": 318, "x": 353}]}, "text": "E", "property": {"detectedBreak": {"type": "SPACE"}, "detectedLanguages": [{"languageCode": "en"}]}}], "property": {"detectedLanguages": [{"languageCode": "en"}]}}, {"boundingBox": {"vertices": [{"y": 307, "x": 357}, {"y": 306, "x": 371}, {"y": 317, "x": 372}, {"y": 318, "x": 358}]}, "symbols": [{"boundingBox": {"vertices": [{"y": 307, "x": 357}, {"y": 307, "x": 363}, {"y": 318, "x": 364}, {"y": 318, "x": 358}]}, "text": "B", "property": {"detectedLanguages": [{"languageCode": "en"}]}}, {"boundingBox": {"vertices": [{"y": 306, "x": 364}, {"y": 306, "x": 365}, {"y": 317, "x": 366}, {"y": 317, "x": 365}]}, "text": "I", "property": {"detectedLanguages": [{"languageCode": "en"}]}}, {"boundingBox": {"vertices": [{"y": 306, "x": 366}, {"y": 306, "x": 369}, {"y": 317, "x": 370}, {"y": 317, "x": 367}]}, "text": "K", "property": {"detectedLanguages": [{"languageCode": "en"}]}}, {"boundingBox": {"vertices": [{"y": 306, "x": 370}, {"y": 306, "x": 371}, {"y": 317, "x": 372}, {"y": 317, "x": 371}]}, "text": "E", "property": {"detectedBreak": {"type": "EOL_SURE_SPACE"}, "detectedLanguages": [{"languageCode": "en"}]}}], "property": {"detectedLanguages": [{"languageCode": "en"}]}}, {"boundingBox": {"vertices": [{"y": 320, "x": 328}, {"y": 317, "x": 358}, {"y": 328, "x": 359}, {"y": 331, "x": 329}]}, "symbols": [{"boundingBox": {"vertices": [{"y": 321, "x": 328}, {"y": 320, "x": 335}, {"y": 330, "x": 336}, {"y": 331, "x": 329}]}, "text": "P", "property": {"detectedLanguages": [{"languageCode": "en"}]}}, {"boundingBox": {"vertices": [{"y": 320, "x": 336}, {"y": 320, "x": 338}, {"y": 330, "x": 339}, {"y": 330, "x": 337}]}, "text": "A", "property": {"detectedLanguages": [{"languageCode": "en"}]}}, {"boundingBox": {"vertices": [{"y": 320, "x": 339}, {"y": 320, "x": 342}, {"y": 330, "x": 343}, {"y": 330, "x": 340}]}, "text": "P", "property": {"detectedLanguages": [{"languageCode": "en"}]}}, {"boundingBox": {"vertices": [{"y": 319, "x": 343}, {"y": 319, "x": 346}, {"y": 329, "x": 347}, {"y": 329, "x": 344}]}, "text": "K", "property": {"detectedLanguages": [{"languageCode": "en"}]}}, {"boundingBox": {"vertices": [{"y": 319, "x": 347}, {"y": 319, "x": 351}, {"y": 329, "x": 352}, {"y": 329, "x": 348}]}, "text": "I", "property": {"detectedLanguages": [{"languageCode": "en"}]}}, {"boundingBox": {"vertices": [{"y": 319, "x": 352}, {"y": 319, "x": 355}, {"y": 329, "x": 356}, {"y": 329, "x": 353}]}, "text": "N", "property": {"detectedLanguages": [{"languageCode": "en"}]}}, {"boundingBox": {"vertices": [{"y": 318, "x": 356}, {"y": 318, "x": 358}, {"y": 328, "x": 359}, {"y": 328, "x": 357}]}, "text": "G", "property": {"detectedBreak": {"type": "SPACE"}, "detectedLanguages": [{"languageCode": "en"}]}}], "property": {"detectedLanguages": [{"languageCode": "en"}]}}, {"boundingBox": {"vertices": [{"y": 317, "x": 360}, {"y": 316, "x": 368}, {"y": 327, "x": 369}, {"y": 328, "x": 361}]}, "symbols": [{"boundingBox": {"vertices": [{"y": 318, "x": 360}, {"y": 318, "x": 364}, {"y": 328, "x": 365}, {"y": 328, "x": 361}]}, "text": "T", "property": {"detectedLanguages": [{"languageCode": "en"}]}}, {"boundingBox": {"vertices": [{"y": 317, "x": 365}, {"y": 317, "x": 368}, {"y": 327, "x": 369}, {"y": 327, "x": 366}]}, "text": "A", "property": {"detectedBreak": {"type": "EOL_SURE_SPACE"}, "detectedLanguages": [{"languageCode": "en"}]}}], "property": {"detectedLanguages": [{"languageCode": "en"}]}}]}]}, {"boundingBox": {"vertices": [{"y": 291, "x": 427}, {"y": 318, "x": 425}, {"y": 317, "x": 415}, {"y": 290, "x": 417}]}, "blockType": "TEXT", "property": {"detectedLanguages": [{"languageCode": "gd", "confidence": 1.0}]}, "paragraphs": [{"boundingBox": {"vertices": [{"y": 291, "x": 427}, {"y": 318, "x": 425}, {"y": 317, "x": 415}, {"y": 290, "x": 417}]}, "property": {"detectedLanguages": [{"languageCode": "gd", "confidence": 1.0}]}, "words": [{"boundingBox": {"vertices": [{"y": 291, "x": 427}, {"y": 318, "x": 425}, {"y": 317, "x": 415}, {"y": 290, "x": 417}]}, "symbols": [{"boundingBox": {"vertices": [{"y": 291, "x": 427}, {"y": 301, "x": 426}, {"y": 300, "x": 416}, {"y": 290, "x": 417}]}, "text": "S", "property": {"detectedLanguages": [{"languageCode": "gd"}]}}, {"boundingBox": {"vertices": [{"y": 302, "x": 426}, {"y": 305, "x": 426}, {"y": 304, "x": 416}, {"y": 301, "x": 416}]}, "text": "T", "property": {"detectedLanguages": [{"languageCode": "gd"}]}}, {"boundingBox": {"vertices": [{"y": 306, "x": 426}, {"y": 309, "x": 426}, {"y": 308, "x": 416}, {"y": 305, "x": 416}]}, "text": "T", "property": {"detectedLanguages": [{"languageCode": "gd"}]}}, {"boundingBox": {"vertices": [{"y": 310, "x": 425}, {"y": 312, "x": 425}, {"y": 311, "x": 415}, {"y": 309, "x": 415}]}, "text": "O", "property": {"detectedLanguages": [{"languageCode": "gd"}]}}, {"boundingBox": {"vertices": [{"y": 313, "x": 425}, {"y": 314, "x": 425}, {"y": 313, "x": 415}, {"y": 312, "x": 415}]}, "text": "I", "property": {"detectedLanguages": [{"languageCode": "gd"}]}}, {"boundingBox": {"vertices": [{"y": 315, "x": 425}, {"y": 318, "x": 425}, {"y": 317, "x": 415}, {"y": 314, "x": 415}]}, "text": "L", "property": {"detectedBreak": {"type": "EOL_SURE_SPACE"}, "detectedLanguages": [{"languageCode": "gd"}]}}], "property": {"detectedLanguages": [{"languageCode": "gd"}]}}]}]}], "height": 335}]}}