{"textAnnotations": [{"locale": "en", "description": "VER CLE\nFERRY\nBRIGANTIA OF BRISTOL\n", "boundingPoly": {"vertices": [{"y": 20, "x": 1}, {"y": 20, "x": 346}, {"y": 255, "x": 346}, {"y": 255, "x": 1}]}}, {"description": "VER", "boundingPoly": {"vertices": [{"y": 20, "x": 1}, {"y": 20, "x": 10}, {"y": 26, "x": 10}, {"y": 26, "x": 1}]}}, {"description": "CLE", "boundingPoly": {"vertices": [{"y": 20, "x": 14}, {"y": 20, "x": 30}, {"y": 26, "x": 30}, {"y": 26, "x": 14}]}}, {"description": "FERRY", "boundingPoly": {"vertices": [{"y": 245, "x": 139}, {"y": 246, "x": 170}, {"y": 255, "x": 170}, {"y": 254, "x": 139}]}}, {"description": "BRIGANTIA", "boundingPoly": {"vertices": [{"y": 248, "x": 238}, {"y": 248, "x": 289}, {"y": 254, "x": 289}, {"y": 254, "x": 238}]}}, {"description": "OF", "boundingPoly": {"vertices": [{"y": 248, "x": 293}, {"y": 248, "x": 305}, {"y": 254, "x": 305}, {"y": 254, "x": 293}]}}, {"description": "BRISTOL", "boundingPoly": {"vertices": [{"y": 247, "x": 309}, {"y": 247, "x": 346}, {"y": 255, "x": 346}, {"y": 255, "x": 309}]}}], "fullTextAnnotation": {"text": "VER CLE\nFERRY\nBRIGANTIA OF BRISTOL\n", "pages": [{"width": 640, "property": {"detectedLanguages": [{"languageCode": "en", "confidence": 0.7900000214576721}, {"languageCode": "es", "confidence": 0.20999999344348907}]}, "blocks": [{"boundingBox": {"vertices": [{"y": 20, "x": 1}, {"y": 19, "x": 30}, {"y": 25, "x": 30}, {"y": 26, "x": 1}]}, "blockType": "TEXT", "property": {"detectedLanguages": [{"languageCode": "es", "confidence": 1.0}]}, "paragraphs": [{"boundingBox": {"vertices": [{"y": 20, "x": 1}, {"y": 19, "x": 30}, {"y": 25, "x": 30}, {"y": 26, "x": 1}]}, "property": {"detectedLanguages": [{"languageCode": "es", "confidence": 1.0}]}, "words": [{"boundingBox": {"vertices": [{"y": 20, "x": 1}, {"y": 20, "x": 10}, {"y": 26, "x": 10}, {"y": 26, "x": 1}]}, "symbols": [{"boundingBox": {"vertices": [{"y": 20, "x": 1}, {"y": 20, "x": 5}, {"y": 26, "x": 5}, {"y": 26, "x": 1}]}, "text": "V", "property": {"detectedLanguages": [{"languageCode": "es"}]}}, {"boundingBox": {"vertices": [{"y": 20, "x": 6}, {"y": 20, "x": 8}, {"y": 26, "x": 8}, {"y": 26, "x": 6}]}, "text": "E", "property": {"detectedLanguages": [{"languageCode": "es"}]}}, {"boundingBox": {"vertices": [{"y": 20, "x": 9}, {"y": 20, "x": 10}, {"y": 26, "x": 10}, {"y": 26, "x": 9}]}, "text": "R", "property": {"detectedBreak": {"type": "SPACE"}, "detectedLanguages": [{"languageCode": "es"}]}}], "property": {"detectedLanguages": [{"languageCode": "es"}]}}, {"boundingBox": {"vertices": [{"y": 20, "x": 14}, {"y": 20, "x": 30}, {"y": 26, "x": 30}, {"y": 26, "x": 14}]}, "symbols": [{"boundingBox": {"vertices": [{"y": 20, "x": 14}, {"y": 20, "x": 18}, {"y": 26, "x": 18}, {"y": 26, "x": 14}]}, "text": "C", "property": {"detectedLanguages": [{"languageCode": "es"}]}}, {"boundingBox": {"vertices": [{"y": 20, "x": 19}, {"y": 20, "x": 24}, {"y": 26, "x": 24}, {"y": 26, "x": 19}]}, "text": "L", "property": {"detectedLanguages": [{"languageCode": "es"}]}}, {"boundingBox": {"vertices": [{"y": 20, "x": 25}, {"y": 20, "x": 30}, {"y": 26, "x": 30}, {"y": 26, "x": 25}]}, "text": "E", "property": {"detectedBreak": {"type": "EOL_SURE_SPACE"}, "detectedLanguages": [{"languageCode": "es"}]}}], "property": {"detectedLanguages": [{"languageCode": "es"}]}}]}]}, {"boundingBox": {"vertices": [{"y": 245, "x": 139}, {"y": 246, "x": 170}, {"y": 255, "x": 170}, {"y": 254, "x": 139}]}, "blockType": "TEXT", "property": {"detectedLanguages": [{"languageCode": "en", "confidence": 1.0}]}, "paragraphs": [{"boundingBox": {"vertices": [{"y": 245, "x": 139}, {"y": 246, "x": 170}, {"y": 255, "x": 170}, {"y": 254, "x": 139}]}, "property": {"detectedLanguages": [{"languageCode": "en", "confidence": 1.0}]}, "words": [{"boundingBox": {"vertices": [{"y": 245, "x": 139}, {"y": 246, "x": 170}, {"y": 255, "x": 170}, {"y": 254, "x": 139}]}, "symbols": [{"boundingBox": {"vertices": [{"y": 245, "x": 139}, {"y": 245, "x": 148}, {"y": 254, "x": 148}, {"y": 254, "x": 139}]}, "text": "F", "property": {"detectedLanguages": [{"languageCode": "en"}]}}, {"boundingBox": {"vertices": [{"y": 245, "x": 149}, {"y": 245, "x": 151}, {"y": 254, "x": 151}, {"y": 254, "x": 149}]}, "text": "E", "property": {"detectedLanguages": [{"languageCode": "en"}]}}, {"boundingBox": {"vertices": [{"y": 245, "x": 152}, {"y": 245, "x": 157}, {"y": 254, "x": 157}, {"y": 254, "x": 152}]}, "text": "R", "property": {"detectedLanguages": [{"languageCode": "en"}]}}, {"boundingBox": {"vertices": [{"y": 245, "x": 158}, {"y": 245, "x": 162}, {"y": 254, "x": 162}, {"y": 254, "x": 158}]}, "text": "R", "property": {"detectedLanguages": [{"languageCode": "en"}]}}, {"boundingBox": {"vertices": [{"y": 246, "x": 163}, {"y": 246, "x": 170}, {"y": 255, "x": 170}, {"y": 255, "x": 163}]}, "text": "Y", "property": {"detectedBreak": {"type": "EOL_SURE_SPACE"}, "detectedLanguages": [{"languageCode": "en"}]}}], "property": {"detectedLanguages": [{"languageCode": "en"}]}}]}]}, {"boundingBox": {"vertices": [{"y": 247, "x": 238}, {"y": 248, "x": 346}, {"y": 255, "x": 346}, {"y": 254, "x": 238}]}, "blockType": "TEXT", "property": {"detectedLanguages": [{"languageCode": "en", "confidence": 1.0}]}, "paragraphs": [{"boundingBox": {"vertices": [{"y": 247, "x": 238}, {"y": 248, "x": 346}, {"y": 255, "x": 346}, {"y": 254, "x": 238}]}, "property": {"detectedLanguages": [{"languageCode": "en", "confidence": 1.0}]}, "words": [{"boundingBox": {"vertices": [{"y": 248, "x": 238}, {"y": 248, "x": 289}, {"y": 254, "x": 289}, {"y": 254, "x": 238}]}, "symbols": [{"boundingBox": {"vertices": [{"y": 248, "x": 238}, {"y": 248, "x": 246}, {"y": 254, "x": 246}, {"y": 254, "x": 238}]}, "text": "B", "property": {"detectedLanguages": [{"languageCode": "en"}]}}, {"boundingBox": {"vertices": [{"y": 248, "x": 247}, {"y": 248, "x": 251}, {"y": 254, "x": 251}, {"y": 254, "x": 247}]}, "text": "R", "property": {"detectedLanguages": [{"languageCode": "en"}]}}, {"boundingBox": {"vertices": [{"y": 248, "x": 252}, {"y": 248, "x": 256}, {"y": 254, "x": 256}, {"y": 254, "x": 252}]}, "text": "I", "property": {"detectedLanguages": [{"languageCode": "en"}]}}, {"boundingBox": {"vertices": [{"y": 248, "x": 257}, {"y": 248, "x": 261}, {"y": 254, "x": 261}, {"y": 254, "x": 257}]}, "text": "G", "property": {"detectedLanguages": [{"languageCode": "en"}]}}, {"boundingBox": {"vertices": [{"y": 248, "x": 262}, {"y": 248, "x": 274}, {"y": 254, "x": 274}, {"y": 254, "x": 262}]}, "text": "A", "property": {"detectedLanguages": [{"languageCode": "en"}]}}, {"boundingBox": {"vertices": [{"y": 248, "x": 275}, {"y": 248, "x": 276}, {"y": 254, "x": 276}, {"y": 254, "x": 275}]}, "text": "N", "property": {"detectedLanguages": [{"languageCode": "en"}]}}, {"boundingBox": {"vertices": [{"y": 248, "x": 277}, {"y": 248, "x": 279}, {"y": 254, "x": 279}, {"y": 254, "x": 277}]}, "text": "T", "property": {"detectedLanguages": [{"languageCode": "en"}]}}, {"boundingBox": {"vertices": [{"y": 248, "x": 280}, {"y": 248, "x": 286}, {"y": 254, "x": 286}, {"y": 254, "x": 280}]}, "text": "I", "property": {"detectedLanguages": [{"languageCode": "en"}]}}, {"boundingBox": {"vertices": [{"y": 248, "x": 287}, {"y": 248, "x": 289}, {"y": 254, "x": 289}, {"y": 254, "x": 287}]}, "text": "A", "property": {"detectedBreak": {"type": "SPACE"}, "detectedLanguages": [{"languageCode": "en"}]}}], "property": {"detectedLanguages": [{"languageCode": "en"}]}}, {"boundingBox": {"vertices": [{"y": 248, "x": 293}, {"y": 248, "x": 305}, {"y": 254, "x": 305}, {"y": 254, "x": 293}]}, "symbols": [{"boundingBox": {"vertices": [{"y": 248, "x": 293}, {"y": 248, "x": 299}, {"y": 254, "x": 299}, {"y": 254, "x": 293}]}, "text": "O", "property": {"detectedLanguages": [{"languageCode": "en"}]}}, {"boundingBox": {"vertices": [{"y": 248, "x": 301}, {"y": 248, "x": 305}, {"y": 254, "x": 305}, {"y": 254, "x": 301}]}, "text": "F", "property": {"detectedBreak": {"type": "SPACE"}, "detectedLanguages": [{"languageCode": "en"}]}}], "property": {"detectedLanguages": [{"languageCode": "en"}]}}, {"boundingBox": {"vertices": [{"y": 247, "x": 309}, {"y": 247, "x": 346}, {"y": 255, "x": 346}, {"y": 255, "x": 309}]}, "symbols": [{"boundingBox": {"vertices": [{"y": 247, "x": 309}, {"y": 247, "x": 316}, {"y": 254, "x": 316}, {"y": 254, "x": 309}]}, "text": "B", "property": {"detectedLanguages": [{"languageCode": "en"}]}}, {"boundingBox": {"vertices": [{"y": 248, "x": 317}, {"y": 248, "x": 321}, {"y": 255, "x": 321}, {"y": 255, "x": 317}]}, "text": "R", "property": {"detectedLanguages": [{"languageCode": "en"}]}}, {"boundingBox": {"vertices": [{"y": 248, "x": 322}, {"y": 248, "x": 329}, {"y": 255, "x": 329}, {"y": 255, "x": 322}]}, "text": "I", "property": {"detectedLanguages": [{"languageCode": "en"}]}}, {"boundingBox": {"vertices": [{"y": 248, "x": 330}, {"y": 248, "x": 333}, {"y": 255, "x": 333}, {"y": 255, "x": 330}]}, "text": "S", "property": {"detectedLanguages": [{"languageCode": "en"}]}}, {"boundingBox": {"vertices": [{"y": 248, "x": 334}, {"y": 248, "x": 336}, {"y": 255, "x": 336}, {"y": 255, "x": 334}]}, "text": "T", "property": {"detectedLanguages": [{"languageCode": "en"}]}}, {"boundingBox": {"vertices": [{"y": 248, "x": 337}, {"y": 248, "x": 344}, {"y": 255, "x": 344}, {"y": 255, "x": 337}]}, "text": "O", "property": {"detectedLanguages": [{"languageCode": "en"}]}}, {"boundingBox": {"vertices": [{"y": 248, "x": 345}, {"y": 248, "x": 346}, {"y": 255, "x": 346}, {"y": 255, "x": 345}]}, "text": "L", "property": {"detectedBreak": {"type": "EOL_SURE_SPACE"}, "detectedLanguages": [{"languageCode": "en"}]}}], "property": {"detectedLanguages": [{"languageCode": "en"}]}}]}]}], "height": 427}]}}